CoegilSdk.py
coegil_sdk-1.0.7.dist-info/METADATA
coegil_sdk-1.0.7.dist-info/WHEEL
coegil_sdk-1.0.7.dist-info/top_level.txt
coegil_sdk-1.0.7.dist-info/RECORD
